src/tools.py
zjutils-0.0.3.dist-info/METADATA
zjutils-0.0.3.dist-info/WHEEL
zjutils-0.0.3.dist-info/top_level.txt
zjutils-0.0.3.dist-info/RECORD
